drift_shield/__init__.py
drift_shield/data_drift.py
drift_shield/delete_drift_dump.py
drift_shield/feature_importance_drift.py
drift_shield/handle_data_drift.py
drift_shield/monitor_data_volume_over_time.py
drift_shield-0.5.dist-info/LICENSE
drift_shield-0.5.dist-info/METADATA
drift_shield-0.5.dist-info/WHEEL
drift_shield-0.5.dist-info/top_level.txt
drift_shield-0.5.dist-info/RECORD
