Metadata-Version: 2.1
Name: drift_shield
Version: 0.5
Summary: A package to monitor and track data drift for ML models
Author: Shanmukh Dara
Author-email: shanmukhdara@gmail.com
Classifier: Programming Language :: Python :: 3
Classifier: License :: OSI Approved :: MIT License
Classifier: Operating System :: OS Independent
Requires-Python: >=3.6
License-File: LICENSE
Requires-Dist: pandas
Requires-Dist: scipy
Requires-Dist: xgboost
Requires-Dist: sklearn
Requires-Dist: shap
